simplyincluded/__init__.py
simplyincluded/simplyincluded.py
simplyincluded-1.0.0.dist-info/LICENSE
simplyincluded-1.0.0.dist-info/METADATA
simplyincluded-1.0.0.dist-info/WHEEL
simplyincluded-1.0.0.dist-info/top_level.txt
simplyincluded-1.0.0.dist-info/RECORD
