Metadata-Version: 2.1
Name: simplyincluded
Version: 1.0.0
Summary: Simple way to find an optimal split.
Author: Howell Lu
Author-email: <hl4631@nyu.edu>
License: UNKNOWN
Keywords: python,pandas,knockout rules,linear optimization,inclusion,exclusion,criteria
Platform: UNKNOWN
Classifier: Development Status :: 1 - Planning
Classifier: Intended Audience :: Education
Classifier: Programming Language :: Python :: 3
Classifier: Operating System :: Unix
Classifier: Operating System :: MacOS :: MacOS X
Classifier: Operating System :: Microsoft :: Windows
License-File: LICENSE
Requires-Dist: pandas
